{"is_source_file": true, "format": "JavaScript", "description": "This file defines a Redux slice named 'boards' using Redux Toolkit's createSlice, managing state related to boards including setting the current board and adding new boards.", "external_files": ["@reduxjs/toolkit"], "external_methods": ["createSlice"], "published": ["setCurrentBoard", "addBoard", "default"], "classes": [], "methods": [{"name": "setCurrentBoard", "description": "Reducer function to set the current board ID."}, {"name": "addBoard", "description": "Reducer function to add a new board to the list."}], "calls": ["createSlice"], "search-terms": ["boards slice", "redux toolkit", "state management", "currentBoardId", "addBoard", "setCurrentBoard"], "state": 2, "file_id": 15, "knowledge_revision": 32, "git_revision": "", "ctags": [{"_type": "tag", "name": "boardsSlice", "path": "/home/kavia/workspace/code-generation/scrumflow-platform-3365-3374/scrum_mind_frontend/src/state/slices/boards.js", "pattern": "/^const boardsSlice = createSlice({$/", "language": "JavaScript", "kind": "constant"}], "hash": "a8cdf1820e26ecaadae56b40723a50ab", "format-version": 4, "code-base-name": "scrum_mind_frontend", "filename": "scrum_mind_frontend/src/state/slices/boards.js", "revision_history": [{"32": ""}]}